py_mistral_helper/MistralHelper.py
py_mistral_helper/__init__.py
py_mistral_helper-0.1.0.dist-info/METADATA
py_mistral_helper-0.1.0.dist-info/WHEEL
py_mistral_helper-0.1.0.dist-info/RECORD
