Metadata-Version: 2.3
Name: py-mistral-helper
Version: 0.1.0
Summary: 
Author: Lav Sharma
Author-email: lavsharma2016@gmail.com
Requires-Python: >=3.12
Classifier: Programming Language :: Python :: 3
Classifier: Programming Language :: Python :: 3.12
Classifier: Programming Language :: Python :: 3.13
Requires-Dist: mistralai (>=1.5.1,<2.0.0)
Requires-Dist: requests (>=2.32.3,<3.0.0)
